[
  {
    "id": "demo-sivra",
    "name": "Sívra Folhargêntea",
    "race": "Elfa da Floresta",
    "classes": [{ "name": "Patrulheira", "level": 5, "subclass": "Caçadora" }],
    "level": 5,
    "abilities": { "str": 12, "dex": 17, "con": 14, "int": 10, "wis": 15, "cha": 8 },
    "hp": 44,
    "maxHp": 44,
    "ac": 16,
    "player": "demo",
    "source": "manual"
  },
  {
    "id": "demo-korgath",
    "name": "Korgath Quebra-Escudos",
    "race": "Meio-Orc",
    "classes": [{ "name": "Bárbaro", "level": 5, "subclass": "Fúria Selvagem" }],
    "level": 5,
    "abilities": { "str": 18, "dex": 13, "con": 16, "int": 8, "wis": 10, "cha": 12 },
    "hp": 58,
    "maxHp": 58,
    "ac": 15,
    "player": "demo",
    "source": "manual"
  },
  {
    "id": "demo-aldo",
    "name": "Frei Aldo",
    "race": "Humano",
    "classes": [{ "name": "Clérigo", "level": 5, "subclass": "Domínio da Vida" }],
    "level": 5,
    "abilities": { "str": 13, "dex": 10, "con": 14, "int": 11, "wis": 17, "cha": 12 },
    "hp": 38,
    "maxHp": 38,
    "ac": 18,
    "player": "demo",
    "source": "manual"
  },
  {
    "id": "demo-pip",
    "name": "Pip Dedolesto",
    "race": "Halfling",
    "classes": [{ "name": "Ladino", "level": 5, "subclass": "Trapaceiro Arcano" }],
    "level": 5,
    "abilities": { "str": 8, "dex": 18, "con": 12, "int": 14, "wis": 13, "cha": 10 },
    "hp": 33,
    "maxHp": 33,
    "ac": 15,
    "player": "demo",
    "source": "manual"
  }
]
